{
  "hymnRich": {
    "blocks": [
      {
        "kind": "stanza",
        "lines": [
          {
            "spans": [
              {
                "kind": "text",
                "text": "Өөрийнхөө замаар хөтлөн дагуулаач"
              }
            ],
            "indent": 0
          },
          {
            "spans": [
              {
                "kind": "text",
                "text": "Зөвхөн Эзэн таныг хүсэмжилж байна"
              }
            ],
            "indent": 0
          },
          {
            "spans": [
              {
                "kind": "text",
                "text": "Үнэн магтаалыг авахын тулд"
              }
            ],
            "indent": 0
          },
          {
            "spans": [
              {
                "kind": "text",
                "text": "Өөрийнхөө хайраар Та дүүргээч"
              }
            ],
            "indent": 0
          },
          {
            "spans": [
              {
                "kind": "text",
                "text": "Цангаж буй миний сүнс Таныг дуудаж байна"
              }
            ],
            "indent": 0
          },
          {
            "spans": [
              {
                "kind": "text",
                "text": "Зүрхэнд минь мутраа хүргээч"
              }
            ],
            "indent": 0
          },
          {
            "spans": [
              {
                "kind": "text",
                "text": "Таныг л хүсэмжилж байна бүр илүүгээр"
              }
            ],
            "indent": 0
          }
        ]
      }
    ],
    "page": 932,
    "source": {
      "kind": "common",
      "id": "hymn-75"
    }
  }
}
