{
  "shortReadingRich": {
    "blocks": [
      {
        "kind": "para",
        "spans": [
          {
            "kind": "text",
            "text": "Ах дүү нар минь, элдвийн сорилтод орохдоо үүнийг бүрэн баяр хөөр гэж үз. Итгэлийн чинь шалгуур хатуужилд хүргэдгийг та нар мэдэх билээ. Хатуужил нь төгс үйл байг. Тэгвэл та нар төгс, бүтэн юугаар ч дутахгүй байна. Харин та нарын хэн нэг нь мэргэн ухаанаар дутвал, бүх хүнд өгөөмрөөр, буруушаалгүй өгөгч Тэнгэрбурханаас гуйг. Тэгээд түүнд өгөгдөх болно. Харин тэр ямар ч эргэлзээгүйгээр итгэлээрээ гуйг. Учир нь эргэлзэгч нэгэн бол салхиар туугдан давалгаалах тэнгисийн долгио мэт ажээ. Тийм хүн Эзэнээс юм авна гэж бүү санаг. Хоёр санаатан нь бүх үйлдээ тогтворгүй байдаг юм."
          }
        ]
      }
    ],
    "page": 387,
    "source": {
      "kind": "psalter-commons",
      "psalterWeek": "3",
      "dayKey": "FRI",
      "hour": "vespers"
    }
  },
  "responsoryRich": {
    "blocks": [
      {
        "kind": "para",
        "spans": [
          {
            "kind": "response",
            "text": "Христ биднийг хайрлаж, Өөрийн цусаараа гэм нүглийг минь арилгасан."
          }
        ]
      },
      {
        "kind": "para",
        "spans": [
          {
            "kind": "versicle",
            "text": "Тэр Өөрийн цусаараа"
          }
        ]
      },
      {
        "kind": "para",
        "spans": [
          {
            "kind": "response",
            "text": "Биднийг хаадын болон тахилч нарын үндэстэн болгосон."
          }
        ]
      },
      {
        "kind": "para",
        "spans": [
          {
            "kind": "text",
            "text": "Эцэг, Хүү, Ариун Сүнсийг магтан дуулъя."
          }
        ]
      },
      {
        "kind": "para",
        "spans": [
          {
            "kind": "response",
            "text": "Христ биднийг хайрлаж, Өөрийн цусаараа гэм нүглийг минь арилгасан."
          }
        ]
      }
    ],
    "page": 388,
    "source": {
      "kind": "common",
      "id": "psalter-w3-fri-vespers-responsory"
    }
  }
}
